stats_dashboard/__init__.py
stats_dashboard/apps.py
stats_dashboard/models.py
stats_dashboard/urls.py
stats_dashboard/views.py
stats_dashboard/charts/__init__.py
stats_dashboard/charts/dataset.py
stats_dashboard/charts/dataset_styles.py
stats_dashboard/charts/manager.py
stats_dashboard/charts/preset.py
stats_dashboard/charts/types.py
stats_dashboard/middleware/__init__.py
stats_dashboard/middleware/stat_middleware.py
stats_dashboard/static/stats/chart.js
stats_dashboard/static/stats/dashboard.js
stats_dashboard/static/stats/graph.svg
stats_dashboard/static/stats/list.svg
stats_dashboard/static/stats/reload.svg
stats_dashboard/static/stats/stats.js
stats_dashboard/static/stats/style.css
stats_dashboard/templates/stats/index.html
django_statistics_dashboard-1.0.dist-info/LICENSE.txt
django_statistics_dashboard-1.0.dist-info/METADATA
django_statistics_dashboard-1.0.dist-info/WHEEL
django_statistics_dashboard-1.0.dist-info/top_level.txt
django_statistics_dashboard-1.0.dist-info/RECORD
