Metadata-Version: 2.1
Name: django-statistics-dashboard
Version: 1.0
Summary: A stats dashboard and session tracker for Django.
Home-page: https://github.com/Si1veR123/django-statistics-dashboard
Author: Connor George
Author-email: connorgeorgeem@aol.com
License: MIT
License-File: LICENSE.txt
